showdoc/__init__.py
showdoc/_modidx.py
showdoc/_nbdev.py
showdoc/lookup.py
showdoc/showdoc.py
showdoc-2.0.1.dist-info/LICENSE
showdoc-2.0.1.dist-info/METADATA
showdoc-2.0.1.dist-info/WHEEL
showdoc-2.0.1.dist-info/entry_points.txt
showdoc-2.0.1.dist-info/top_level.txt
showdoc-2.0.1.dist-info/RECORD
