Metadata-Version: 2.1
Name: showdoc
Version: 2.0.1
Summary: Documentation lookup from nbdev index
Home-page: https://github.com/fastai/showdoc/tree/master/
Author: Jeremy Howard and Sylvain Gugger
Author-email: info@fast.ai
License: Apache Software License 2.0
Keywords: jupyter notebook
Platform: UNKNOWN
Classifier: Development Status :: 5 - Production/Stable
Classifier: Intended Audience :: Developers
Classifier: License :: OSI Approved :: Apache Software License
Classifier: Natural Language :: English
Classifier: Programming Language :: Python :: 3.6
Classifier: Programming Language :: Python :: 3.7
Classifier: Programming Language :: Python :: 3.8
Requires-Python: >=3.6
Requires-Dist: pip
Requires-Dist: packaging
Requires-Dist: fastcore (>=1.2.2)
Provides-Extra: dev
